README.rst
geoselect.py
setup.py
geoselect.egg-info/PKG-INFO
geoselect.egg-info/SOURCES.txt
geoselect.egg-info/dependency_links.txt
geoselect.egg-info/entry_points.txt
geoselect.egg-info/requires.txt
geoselect.egg-info/top_level.txt