Metadata-Version: 1.1
Name: geoselect
Version: 0.2.2
Summary: A script to select photos from a set, based on geographical location.
Home-page: https://github.com/FreekKalter/geoselect
Author: Freek Kalter
Author-email: freek@kalteronline.org
License: GPL v3
Keywords: gps photos filter
Platform: UNKNOWN
Classifier: Development Status :: 3 - Alpha
Classifier: License :: OSI Approved :: GNU General Public License v3 (GPLv3)
Classifier: Environment :: Console
Classifier: Programming Language :: Python :: 2.7
Classifier: Topic :: Utilities
Classifier: Topic :: Multimedia
